onnxruntime_genai/LICENSE
onnxruntime_genai/ThirdPartyNotices.txt
onnxruntime_genai/__init__.py
onnxruntime_genai/_dll_directory.py
onnxruntime_genai/libonnxruntime-genai-cuda.so
onnxruntime_genai/libonnxruntime-genai.so
onnxruntime_genai/onnxruntime_genai.cpython-311-x86_64-linux-gnu.so
onnxruntime_genai/models/__init__.py
onnxruntime_genai/models/builder.py
onnxruntime_genai/models/gguf_model.py
onnxruntime_genai/models/quantized_model.py
onnxruntime_genai/models/builders/__init__.py
onnxruntime_genai/models/builders/base.py
onnxruntime_genai/models/builders/chatglm.py
onnxruntime_genai/models/builders/ernie.py
onnxruntime_genai/models/builders/gemma.py
onnxruntime_genai/models/builders/gptoss.py
onnxruntime_genai/models/builders/granite.py
onnxruntime_genai/models/builders/llama.py
onnxruntime_genai/models/builders/mistral.py
onnxruntime_genai/models/builders/nemotron.py
onnxruntime_genai/models/builders/olmo.py
onnxruntime_genai/models/builders/phi.py
onnxruntime_genai/models/builders/qwen.py
onnxruntime_genai/models/builders/smollm.py
onnxruntime_genai_cuda-0.11.4.dist-info/METADATA
onnxruntime_genai_cuda-0.11.4.dist-info/WHEEL
onnxruntime_genai_cuda-0.11.4.dist-info/top_level.txt
onnxruntime_genai_cuda-0.11.4.dist-info/RECORD
